MANIFEST.in
README.md
requirements.txt
setup.py
piper/__init__.py
piper/__main__.py
piper/cli/__init__.py
piper/cli/base.py
piper/cli/blueprinter.py
piper/cli/cleaner.py
piper/cli/packer.py
piper/cli/python_wrapper.py
piper/cli/setupper.py
piper/config/__init__.py
piper/config/pipe.py
piper/config/reader.py
piper/config/sanitizers/__init__.py
piper/config/sanitizers/asserter.py
piper/config/sanitizers/name_sanitizer.py
piper/config/sanitizers/pip_sanitizer.py
piper/config/sanitizers/python_sanitizer.py
piper/config/subconfigs/__init__.py
piper/config/subconfigs/pip.py
piper/config/subconfigs/scopes.py
piper/custom/__init__.py
piper/custom/scopes/__init__.py
piper/custom/scopes/scoped_venvs.py
piper/custom/tasks/__init__.py
piper/custom/tasks/performer.py
piper/custom/tasks/task.py
piper/resources/blueprint/generate.py
piper/resources/tasks/perform.py
piper/tools/__init__.py
piper/tools/base_venv.py
piper/tools/executable.py
piper/tools/pip.py
piper/tools/python.py
piper/tools/shell.py
piper/tools/venv.py
piper_tools.egg-info/PKG-INFO
piper_tools.egg-info/SOURCES.txt
piper_tools.egg-info/dependency_links.txt
piper_tools.egg-info/entry_points.txt
piper_tools.egg-info/requires.txt
piper_tools.egg-info/top_level.txt